inventree_wireviz/__init__.py
inventree_wireviz/processing.py
inventree_wireviz/serializers.py
inventree_wireviz/views.py
inventree_wireviz/wireviz.py
inventree_wireviz/static/WirevizDashboard.js
inventree_wireviz/static/WirevizPanel.js
inventree_wireviz/static/WirevizSettings.js
inventree_wireviz/static/assets/Navigation-yUMBvUKs.js
inventree_wireviz/static/assets/createReactComponent--Uuatr69.js
inventree_wireviz_plugin-1.1.1.dist-info/licenses/LICENSE
inventree_wireviz_plugin-1.1.1.dist-info/METADATA
inventree_wireviz_plugin-1.1.1.dist-info/WHEEL
inventree_wireviz_plugin-1.1.1.dist-info/entry_points.txt
inventree_wireviz_plugin-1.1.1.dist-info/top_level.txt
inventree_wireviz_plugin-1.1.1.dist-info/RECORD
