Metadata-Version: 2.4
Name: inventree-wireviz-plugin
Version: 1.1.1
Summary: Wireviz plugin for InvenTree
Home-page: https://github.com/inventree/inventree-wireviz
Author: Oliver Walters
Author-email: oliver.henry.walters@gmail.com
License: MIT
Keywords: inventree inventory wireviz wiring cable harness
Classifier: Programming Language :: Python :: 3
Classifier: Operating System :: OS Independent
Classifier: Framework :: InvenTree
Requires-Python: >=3.9
License-File: LICENSE
Requires-Dist: wireviz>=0.4.1
Requires-Dist: pint>=0.24.4
Dynamic: author
Dynamic: author-email
Dynamic: classifier
Dynamic: description
Dynamic: description-content-type
Dynamic: home-page
Dynamic: keywords
Dynamic: license
Dynamic: license-file
Dynamic: requires-dist
Dynamic: requires-python
Dynamic: summary
